dingding_webhook/__init__.py
dingding_webhook/webhook.py
dingding_webhook-0.0.3.dist-info/LICENSE
dingding_webhook-0.0.3.dist-info/METADATA
dingding_webhook-0.0.3.dist-info/WHEEL
dingding_webhook-0.0.3.dist-info/top_level.txt
dingding_webhook-0.0.3.dist-info/RECORD
