Metadata-Version: 2.1
Name: dingding-webhook
Version: 0.0.3
Summary: A simple api for dingding robot
Home-page: https://github.com/nowindxdw/dingdingwebhook
Author: nowindxdw
Author-email: nowindxdw@126.com
License: UNKNOWN
Platform: UNKNOWN
Classifier: Programming Language :: Python :: 2
Classifier: License :: OSI Approved :: MIT License
Classifier: Operating System :: OS Independent
Requires-Python: >=2.7
